{
  "prototypeToken": {
    "displayName": 20,
    "displayBars": 20,
    "flags": {
      "pf2e": {
        "linkToActorSize": true,
        "autoscale": false
      }
    },
    "height": 1,
    "width": 1,
    "name": "Black Company",
    "actorLink": false,
    "appendNumber": false,
    "prependAdjective": false,
    "texture": {
      "src": "systems/pf2e/icons/default-icons/npc.svg",
      "scaleX": 2,
      "scaleY": 2,
      "offsetX": 0,
      "offsetY": 0,
      "rotation": 0,
      "tint": "#ffffff",
      "anchorX": 0.5,
      "anchorY": 0.5,
      "fit": "contain",
      "alphaThreshold": 0.75
    },
    "lockRotation": true,
    "rotation": 0,
    "alpha": 1,
    "disposition": -1,
    "bar1": {
      "attribute": "attributes.hp"
    },
    "bar2": {
      "attribute": "attributes.shield.hp"
    },
    "light": {
      "alpha": 0.5,
      "angle": 360,
      "bright": 0,
      "coloration": 1,
      "dim": 0,
      "attenuation": 0.5,
      "luminosity": 0.5,
      "saturation": 0,
      "contrast": 0,
      "shadows": 0,
      "animation": {
        "type": null,
        "speed": 5,
        "intensity": 5,
        "reverse": false
      },
      "darkness": {
        "min": 0,
        "max": 1
      },
      "color": null,
      "negative": false,
      "priority": 0
    },
    "sight": {
      "enabled": false,
      "range": 0,
      "angle": 360,
      "visionMode": "basic",
      "attenuation": 0.1,
      "brightness": 0,
      "saturation": 0,
      "contrast": 0,
      "color": null
    },
    "detectionModes": [],
    "randomImg": false,
    "hexagonalShape": 0,
    "occludable": {
      "radius": 0
    },
    "ring": {
      "enabled": false,
      "colors": {
        "ring": null,
        "background": null
      },
      "effects": 1,
      "subject": {
        "scale": 1,
        "texture": null
      }
    }
  },
  "name": "Black Company",
  "type": "npc",
  "effects": [],
  "system": {
    "attributes": {
      "hp": {
        "value": 60,
        "temp": 0,
        "max": 60,
        "details": ""
      },
      "speed": {
        "value": 25,
        "otherSpeeds": [],
        "details": ""
      },
      "ac": {
        "value": 21,
        "details": "(23 with shield raised)"
      },
      "allSaves": {
        "value": ""
      },
      "resistances": [
        {
          "type": "slashing",
          "value": 1,
          "exceptions": [],
          "doubleVs": []
        }
      ]
    },
    "initiative": {
      "statistic": "perception"
    },
    "details": {
      "languages": {
        "value": [],
        "details": ""
      },
      "level": {
        "value": 4
      },
      "blurb": "",
      "publicNotes": "",
      "privateNotes": "",
      "publication": {
        "title": "",
        "authors": "",
        "license": "OGL",
        "remaster": false
      },
      "creatureType": ""
    },
    "resources": {},
    "_migration": {
      "version": 0.932,
      "previous": {
        "schema": 0.844,
        "foundry": "12.331",
        "system": "6.2.2"
      }
    },
    "abilities": {
      "str": {
        "mod": 5
      },
      "dex": {
        "mod": 2
      },
      "con": {
        "mod": 2
      },
      "int": {
        "mod": 0
      },
      "wis": {
        "mod": 3
      },
      "cha": {
        "mod": 0
      }
    },
    "perception": {
      "details": "",
      "mod": 11,
      "senses": [],
      "vision": true
    },
    "saves": {
      "fortitude": {
        "value": 11,
        "saveDetail": ""
      },
      "reflex": {
        "value": 8,
        "saveDetail": ""
      },
      "will": {
        "value": 14,
        "saveDetail": ""
      }
    },
    "skills": {
      "athletics": {
        "base": 12
      }
    },
    "traits": {
      "value": [
        "human",
        "humanoid",
        "lawful"
      ],
      "rarity": "common",
      "size": {
        "value": "med"
      }
    }
  },
  "img": "modules/memoirs-of-grund/assets/tokens/HumanoidBrytthBlackCompany.png",
  "items": [
    {
      "img": "systems/pf2e/icons/equipment/weapons/longsword.webp",
      "name": "Longsword",
      "system": {
        "description": {
          "gm": "",
          "value": "<p>Longswords can be one‑edged or two‑edged swords. Their blades are heavy and they're between 3 and 4 feet in length.</p>"
        },
        "rules": [],
        "slug": "longsword",
        "_migration": {
          "version": 0.932,
          "lastMigration": null,
          "previous": {
            "schema": 0.844,
            "foundry": "12.331",
            "system": "6.2.2"
          }
        },
        "traits": {
          "otherTags": [],
          "value": [
            "versatile-p"
          ],
          "rarity": "common"
        },
        "publication": {
          "title": "Pathfinder Core Rulebook",
          "authors": "",
          "license": "OGL",
          "remaster": false
        },
        "level": {
          "value": 0
        },
        "quantity": 1,
        "baseItem": "longsword",
        "bulk": {
          "value": 1
        },
        "hp": {
          "value": 0,
          "max": 0
        },
        "hardness": 0,
        "price": {
          "value": {
            "gp": 1
          }
        },
        "equipped": {
          "carryType": "held",
          "invested": null,
          "handsHeld": 1
        },
        "containerId": null,
        "size": "med",
        "material": {
          "type": null,
          "grade": null
        },
        "identification": {
          "status": "identified",
          "unidentified": {
            "name": "",
            "img": "",
            "data": {
              "description": {
                "value": ""
              }
            }
          },
          "misidentified": {}
        },
        "usage": {
          "value": "held-in-one-hand"
        },
        "category": "martial",
        "group": "sword",
        "bonus": {
          "value": 0
        },
        "damage": {
          "dice": 1,
          "die": "d8",
          "damageType": "slashing",
          "persistent": null
        },
        "bonusDamage": {
          "value": 0
        },
        "splashDamage": {
          "value": 0
        },
        "range": null,
        "reload": {
          "value": ""
        },
        "runes": {
          "potency": 0,
          "striking": 0,
          "property": []
        },
        "specific": null,
        "subitems": [],
        "property1": {
          "value": "",
          "dice": 0,
          "die": "",
          "damageType": "",
          "critDice": 0,
          "critDie": "",
          "critDamage": "",
          "critDamageType": ""
        }
      },
      "type": "weapon",
      "flags": {
        "core": {
          "sourceId": "Compendium.pf2e.equipment-srd.Item.LJdbVTOZog39EEbi"
        }
      },
      "effects": [],
      "folder": null,
      "sort": 0,
      "ownership": {
        "default": 0,
        "zGBP0faGe9s57rxO": 3
      },
      "_stats": {
        "compendiumSource": "Compendium.pf2e.equipment-srd.Item.LJdbVTOZog39EEbi",
        "duplicateSource": null,
        "coreVersion": "12.331",
        "systemId": "pf2e",
        "systemVersion": "6.2.2",
        "createdTime": null,
        "modifiedTime": null,
        "lastModifiedBy": null
      },
      "_id": "dQS80cswnOggKyz2"
    },
    {
      "img": "systems/pf2e/icons/equipment/shields/steel-shield.webp",
      "name": "Steel Shield",
      "system": {
        "description": {
          "gm": "",
          "value": "<p>Like wooden shields, steel shields come in a variety of shapes and sizes. Though more expensive than wooden shields, they are much more durable.</p>\n<table class=\"pf2-table\">\n<thead>\n<tr>\n<th>Hardness</th>\n<th>HP</th>\n<th>BT</th>\n</tr>\n</thead>\n<tbody>\n<tr>\n<td>5</td>\n<td>20</td>\n<td>10</td>\n</tr>\n</tbody>\n</table>"
        },
        "rules": [],
        "slug": "steel-shield",
        "_migration": {
          "version": 0.932,
          "lastMigration": null,
          "previous": {
            "schema": 0.844,
            "foundry": "12.331",
            "system": "6.2.2"
          }
        },
        "traits": {
          "otherTags": [],
          "value": [],
          "rarity": "common",
          "integrated": null
        },
        "publication": {
          "title": "Pathfinder Core Rulebook",
          "authors": "",
          "license": "OGL",
          "remaster": false
        },
        "level": {
          "value": 0
        },
        "quantity": 1,
        "baseItem": "steel-shield",
        "bulk": {
          "value": 1
        },
        "hp": {
          "value": 20,
          "max": 20
        },
        "hardness": 5,
        "price": {
          "value": {
            "gp": 2
          }
        },
        "equipped": {
          "carryType": "held",
          "invested": null,
          "handsHeld": 1
        },
        "containerId": null,
        "size": "med",
        "material": {
          "type": null,
          "grade": null
        },
        "identification": {
          "status": "identified",
          "unidentified": {
            "name": "",
            "img": "",
            "data": {
              "description": {
                "value": ""
              }
            }
          },
          "misidentified": {}
        },
        "acBonus": 2,
        "runes": {
          "reinforcing": 0,
          "potency": 0,
          "resilient": 0,
          "property": []
        },
        "specific": null,
        "speedPenalty": 0,
        "subitems": [],
        "dex": {
          "value": 0
        }
      },
      "type": "shield",
      "flags": {
        "core": {
          "sourceId": "Compendium.pf2e.equipment-srd.Item.Yr9yCuJiAlFh3QEB"
        }
      },
      "effects": [],
      "folder": null,
      "sort": 0,
      "ownership": {
        "default": 0,
        "zGBP0faGe9s57rxO": 3
      },
      "_stats": {
        "compendiumSource": "Compendium.pf2e.equipment-srd.Item.Yr9yCuJiAlFh3QEB",
        "duplicateSource": null,
        "coreVersion": "12.331",
        "systemId": "pf2e",
        "systemVersion": "6.2.2",
        "createdTime": null,
        "modifiedTime": null,
        "lastModifiedBy": null
      },
      "_id": "etAcJeGeujcQF6FN"
    },
    {
      "img": "systems/pf2e/icons/equipment/weapons/greatpick.webp",
      "name": "Greatpick",
      "system": {
        "description": {
          "gm": "",
          "value": "<p>This pick has a longer handle and broader head than a regular pick. It is too heavy to wield in one hand.</p>"
        },
        "rules": [],
        "slug": "greatpick",
        "_migration": {
          "version": 0.932,
          "lastMigration": null,
          "previous": {
            "schema": 0.844,
            "foundry": "12.331",
            "system": "6.2.2"
          }
        },
        "traits": {
          "otherTags": [],
          "value": [
            "fatal-d12"
          ],
          "rarity": "common"
        },
        "publication": {
          "title": "Pathfinder Core Rulebook",
          "authors": "",
          "license": "OGL",
          "remaster": false
        },
        "level": {
          "value": 0
        },
        "quantity": 1,
        "baseItem": "greatpick",
        "bulk": {
          "value": 2
        },
        "hp": {
          "value": 0,
          "max": 0
        },
        "hardness": 0,
        "price": {
          "value": {
            "gp": 2
          }
        },
        "equipped": {
          "carryType": "worn",
          "invested": null,
          "handsHeld": 0
        },
        "containerId": null,
        "size": "med",
        "material": {
          "type": null,
          "grade": null
        },
        "identification": {
          "status": "identified",
          "unidentified": {
            "name": "",
            "img": "",
            "data": {
              "description": {
                "value": ""
              }
            }
          },
          "misidentified": {}
        },
        "usage": {
          "value": "held-in-two-hands"
        },
        "category": "martial",
        "group": "pick",
        "bonus": {
          "value": 0
        },
        "damage": {
          "dice": 1,
          "die": "d10",
          "damageType": "piercing",
          "persistent": null
        },
        "bonusDamage": {
          "value": 0
        },
        "splashDamage": {
          "value": 0
        },
        "range": null,
        "reload": {
          "value": ""
        },
        "runes": {
          "potency": 0,
          "striking": 0,
          "property": []
        },
        "specific": null,
        "subitems": [],
        "property1": {
          "value": "",
          "dice": 0,
          "die": "",
          "damageType": "",
          "critDice": 0,
          "critDie": "",
          "critDamage": "",
          "critDamageType": ""
        }
      },
      "type": "weapon",
      "flags": {
        "core": {
          "sourceId": "Compendium.pf2e.equipment-srd.Item.3Zv5hSXXtlaDatUv"
        }
      },
      "effects": [],
      "folder": null,
      "sort": 0,
      "ownership": {
        "default": 0,
        "zGBP0faGe9s57rxO": 3
      },
      "_stats": {
        "compendiumSource": "Compendium.pf2e.equipment-srd.Item.3Zv5hSXXtlaDatUv",
        "duplicateSource": null,
        "coreVersion": "12.331",
        "systemId": "pf2e",
        "systemVersion": "6.2.2",
        "createdTime": null,
        "modifiedTime": null,
        "lastModifiedBy": null
      },
      "_id": "HeuPSFbUF0hKOcWN"
    },
    {
      "name": "Greatpick",
      "type": "melee",
      "system": {
        "description": {
          "gm": "",
          "value": ""
        },
        "rules": [],
        "slug": null,
        "traits": {
          "value": [
            "fatal-d12"
          ],
          "otherTags": []
        },
        "damageRolls": {
          "OIKHFvVBrQNqX2VT": {
            "damage": "1d10+7",
            "damageType": "piercing",
            "category": null
          }
        },
        "bonus": {
          "value": 14
        },
        "attackEffects": {
          "value": []
        },
        "publication": {
          "title": "",
          "authors": "",
          "license": "OGL",
          "remaster": false
        },
        "_migration": {
          "version": 0.932,
          "previous": {
            "schema": null,
            "foundry": "12.331",
            "system": "6.2.2"
          }
        }
      },
      "flags": {
        "pf2e": {
          "linkedWeapon": "HeuPSFbUF0hKOcWN"
        }
      },
      "_id": "elWpey2dLB6NC0Wd",
      "img": "systems/pf2e/icons/default-icons/melee.svg",
      "effects": [],
      "folder": null,
      "sort": 0,
      "ownership": {
        "default": 0,
        "zGBP0faGe9s57rxO": 3
      },
      "_stats": {
        "compendiumSource": null,
        "duplicateSource": null,
        "coreVersion": "12.331",
        "systemId": "pf2e",
        "systemVersion": "6.2.2",
        "createdTime": null,
        "modifiedTime": null,
        "lastModifiedBy": null
      }
    },
    {
      "img": "systems/pf2e/icons/actions/Reaction.webp",
      "name": "Attack of Opportunity",
      "system": {
        "description": {
          "gm": "",
          "value": "<p><strong>Trigger</strong> A creature within your reach uses a manipulate action or a move action, makes a ranged attack, or leaves a square during a move action it's using.</p>\n<hr />\n<p>You lash out at a foe that leaves an opening. Make a melee Strike against the triggering creature. If your attack is a critical hit and the trigger was a manipulate action, you disrupt that action. This Strike doesn't count toward your multiple attack penalty, and your multiple attack penalty doesn't apply to this Strike.</p>"
        },
        "rules": [],
        "slug": "attack-of-opportunity",
        "_migration": {
          "version": 0.932,
          "lastMigration": null,
          "previous": {
            "schema": 0.844,
            "foundry": "12.331",
            "system": "6.2.2"
          }
        },
        "traits": {
          "otherTags": [],
          "value": [],
          "rarity": "common"
        },
        "publication": {
          "title": "Pathfinder Core Rulebook",
          "authors": "",
          "license": "OGL",
          "remaster": false
        },
        "actionType": {
          "value": "reaction"
        },
        "category": null,
        "actions": {
          "value": null
        },
        "deathNote": false,
        "requirements": {
          "value": ""
        },
        "trigger": {
          "value": ""
        }
      },
      "type": "action",
      "flags": {
        "core": {
          "sourceId": "Compendium.pf2e.actionspf2e.Item.KAVf7AmRnbCAHrkT"
        }
      },
      "effects": [],
      "folder": null,
      "sort": 0,
      "ownership": {
        "default": 0,
        "zGBP0faGe9s57rxO": 3
      },
      "_stats": {
        "compendiumSource": "Compendium.pf2e.actionspf2e.Item.KAVf7AmRnbCAHrkT",
        "duplicateSource": null,
        "coreVersion": "12.331",
        "systemId": "pf2e",
        "systemVersion": "6.2.2",
        "createdTime": null,
        "modifiedTime": null,
        "lastModifiedBy": null
      },
      "_id": "ZwtJiSmY26okCMHb"
    },
    {
      "img": "systems/pf2e/icons/actions/Reaction.webp",
      "name": "Shield Block",
      "system": {
        "description": {
          "gm": "",
          "value": "<p>@Localize[PF2E.NPC.Abilities.Glossary.ShieldBlock]</p>"
        },
        "rules": [],
        "slug": "shield-block",
        "_migration": {
          "version": 0.932,
          "lastMigration": null,
          "previous": {
            "schema": 0.844,
            "foundry": "12.331",
            "system": "6.2.2"
          }
        },
        "traits": {
          "otherTags": [],
          "value": [],
          "rarity": "common"
        },
        "publication": {
          "title": "Pathfinder Bestiary",
          "authors": "",
          "license": "OGL",
          "remaster": false
        },
        "actionType": {
          "value": "reaction"
        },
        "category": "defensive",
        "actions": {
          "value": null
        },
        "deathNote": false,
        "requirements": {
          "value": ""
        },
        "trigger": {
          "value": ""
        },
        "weapon": {
          "value": ""
        }
      },
      "type": "action",
      "flags": {
        "core": {
          "sourceId": "Compendium.pf2e.bestiary-ability-glossary-srd.Item.m4HQ2o5aPxjXf2kY"
        }
      },
      "effects": [],
      "folder": null,
      "sort": 0,
      "ownership": {
        "default": 0,
        "zGBP0faGe9s57rxO": 3
      },
      "_stats": {
        "compendiumSource": "Compendium.pf2e.bestiary-ability-glossary-srd.Item.m4HQ2o5aPxjXf2kY",
        "duplicateSource": null,
        "coreVersion": "12.331",
        "systemId": "pf2e",
        "systemVersion": "6.2.2",
        "createdTime": null,
        "modifiedTime": null,
        "lastModifiedBy": null
      },
      "_id": "O20h32AWTb6vCu5v"
    },
    {
      "name": "Longsword",
      "type": "melee",
      "system": {
        "description": {
          "gm": "",
          "value": ""
        },
        "rules": [],
        "slug": null,
        "traits": {
          "value": [
            "versatile-p"
          ],
          "otherTags": []
        },
        "damageRolls": {
          "EuPgdyLiHBy4qfoo": {
            "damage": "1d8+7",
            "damageType": "slashing",
            "category": null
          }
        },
        "bonus": {
          "value": 14
        },
        "attackEffects": {
          "value": []
        },
        "publication": {
          "title": "",
          "authors": "",
          "license": "OGL",
          "remaster": false
        },
        "_migration": {
          "version": 0.932,
          "previous": {
            "schema": null,
            "foundry": "12.331",
            "system": "6.2.2"
          }
        }
      },
      "flags": {
        "pf2e": {}
      },
      "_id": "M2grEfStLLrkEe2v",
      "img": "systems/pf2e/icons/default-icons/melee.svg",
      "effects": [],
      "folder": null,
      "sort": 0,
      "ownership": {
        "default": 0,
        "zGBP0faGe9s57rxO": 3
      },
      "_stats": {
        "compendiumSource": null,
        "duplicateSource": null,
        "coreVersion": "12.331",
        "systemId": "pf2e",
        "systemVersion": "6.2.2",
        "createdTime": null,
        "modifiedTime": null,
        "lastModifiedBy": null
      }
    },
    {
      "img": "systems/pf2e/icons/equipment/weapons/dagger.webp",
      "name": "Dagger",
      "system": {
        "description": {
          "gm": "",
          "value": "<p>This small, bladed weapon is held in one hand and used to stab a creature in close combat. It can also be thrown.</p>"
        },
        "rules": [],
        "slug": "dagger",
        "_migration": {
          "version": 0.932,
          "lastMigration": null,
          "previous": {
            "schema": 0.844,
            "foundry": "12.331",
            "system": "6.2.2"
          }
        },
        "traits": {
          "otherTags": [],
          "value": [
            "agile",
            "finesse",
            "thrown-10",
            "versatile-s"
          ],
          "rarity": "common"
        },
        "publication": {
          "title": "Pathfinder Core Rulebook",
          "authors": "",
          "license": "OGL",
          "remaster": false
        },
        "level": {
          "value": 0
        },
        "quantity": 1,
        "baseItem": "dagger",
        "bulk": {
          "value": 0.1
        },
        "hp": {
          "value": 0,
          "max": 0
        },
        "hardness": 0,
        "price": {
          "value": {
            "sp": 2
          }
        },
        "equipped": {
          "carryType": "worn",
          "invested": null,
          "handsHeld": 0
        },
        "containerId": null,
        "size": "med",
        "material": {
          "type": null,
          "grade": null
        },
        "identification": {
          "status": "identified",
          "unidentified": {
            "name": "",
            "img": "",
            "data": {
              "description": {
                "value": ""
              }
            }
          },
          "misidentified": {}
        },
        "usage": {
          "value": "held-in-one-hand"
        },
        "category": "simple",
        "group": "knife",
        "bonus": {
          "value": 0
        },
        "damage": {
          "dice": 1,
          "die": "d4",
          "damageType": "piercing",
          "persistent": null
        },
        "bonusDamage": {
          "value": 0
        },
        "splashDamage": {
          "value": 0
        },
        "range": null,
        "reload": {
          "value": "-"
        },
        "runes": {
          "potency": 0,
          "striking": 0,
          "property": []
        },
        "specific": null,
        "subitems": [],
        "property1": {
          "value": "",
          "dice": 0,
          "die": "",
          "damageType": "",
          "critDice": 0,
          "critDie": "",
          "critDamage": "",
          "critDamageType": ""
        }
      },
      "type": "weapon",
      "flags": {
        "core": {
          "sourceId": "Compendium.pf2e.equipment-srd.Item.rQWaJhI5Bko5x14Z"
        }
      },
      "effects": [],
      "folder": null,
      "sort": 0,
      "ownership": {
        "default": 0,
        "zGBP0faGe9s57rxO": 3
      },
      "_stats": {
        "compendiumSource": "Compendium.pf2e.equipment-srd.Item.rQWaJhI5Bko5x14Z",
        "duplicateSource": null,
        "coreVersion": "12.331",
        "systemId": "pf2e",
        "systemVersion": "6.2.2",
        "createdTime": null,
        "modifiedTime": null,
        "lastModifiedBy": null
      },
      "_id": "N4edRBjdblDSqwiv"
    },
    {
      "name": "Dagger",
      "type": "melee",
      "system": {
        "description": {
          "gm": "",
          "value": ""
        },
        "rules": [],
        "slug": null,
        "traits": {
          "value": [
            "agile",
            "finesse",
            "versatile-s"
          ],
          "otherTags": []
        },
        "damageRolls": {
          "bSuuxajUxkxgxEh7": {
            "damage": "1d4+7",
            "damageType": "piercing",
            "category": null
          }
        },
        "bonus": {
          "value": 14
        },
        "attackEffects": {
          "value": []
        },
        "publication": {
          "title": "",
          "authors": "",
          "license": "OGL",
          "remaster": false
        },
        "_migration": {
          "version": 0.932,
          "previous": {
            "schema": null,
            "foundry": "12.331",
            "system": "6.2.2"
          }
        }
      },
      "flags": {
        "pf2e": {
          "linkedWeapon": "N4edRBjdblDSqwiv"
        }
      },
      "_id": "jTW8I5akb5foOurV",
      "img": "systems/pf2e/icons/default-icons/melee.svg",
      "effects": [],
      "folder": null,
      "sort": 0,
      "ownership": {
        "default": 0,
        "zGBP0faGe9s57rxO": 3
      },
      "_stats": {
        "compendiumSource": null,
        "duplicateSource": null,
        "coreVersion": "12.331",
        "systemId": "pf2e",
        "systemVersion": "6.2.2",
        "createdTime": null,
        "modifiedTime": null,
        "lastModifiedBy": null
      }
    },
    {
      "name": "Dagger",
      "type": "melee",
      "system": {
        "description": {
          "gm": "",
          "value": ""
        },
        "rules": [],
        "slug": null,
        "traits": {
          "value": [
            "agile",
            "thrown-10",
            "versatile-s"
          ],
          "otherTags": []
        },
        "damageRolls": {
          "f7TACppgctKTMvIC": {
            "damage": "1d4+7",
            "damageType": "piercing",
            "category": null
          }
        },
        "bonus": {
          "value": 14
        },
        "attackEffects": {
          "value": []
        },
        "publication": {
          "title": "",
          "authors": "",
          "license": "OGL",
          "remaster": false
        },
        "_migration": {
          "version": 0.932,
          "previous": {
            "schema": null,
            "foundry": "12.331",
            "system": "6.2.2"
          }
        }
      },
      "flags": {
        "pf2e": {
          "linkedWeapon": "N4edRBjdblDSqwiv"
        }
      },
      "_id": "Ku1tAfVcMzOUBext",
      "img": "systems/pf2e/icons/default-icons/melee.svg",
      "effects": [],
      "folder": null,
      "sort": 0,
      "ownership": {
        "default": 0,
        "zGBP0faGe9s57rxO": 3
      },
      "_stats": {
        "compendiumSource": null,
        "duplicateSource": null,
        "coreVersion": "12.331",
        "systemId": "pf2e",
        "systemVersion": "6.2.2",
        "createdTime": null,
        "modifiedTime": null,
        "lastModifiedBy": null
      }
    },
    {
      "img": "systems/pf2e/icons/equipment/armor/chainmail.webp",
      "name": "Chain Mail",
      "system": {
        "description": {
          "gm": "",
          "value": "<p>A suit of chain mail consists of several pieces of armor composed of small metal rings linked together in a protective mesh. It typically includes a chain shirt, leggings, a pair of arms, and a coif, collectively protecting most of the body.</p>"
        },
        "rules": [],
        "slug": "chain-mail",
        "_migration": {
          "version": 0.932,
          "lastMigration": null,
          "previous": {
            "schema": 0.844,
            "foundry": "12.331",
            "system": "6.2.2"
          }
        },
        "traits": {
          "otherTags": [],
          "value": [
            "flexible",
            "noisy"
          ],
          "rarity": "common"
        },
        "publication": {
          "title": "Pathfinder Core Rulebook",
          "authors": "",
          "license": "OGL",
          "remaster": false
        },
        "level": {
          "value": 0
        },
        "quantity": 1,
        "baseItem": "chain-mail",
        "bulk": {
          "value": 2
        },
        "hp": {
          "value": 0,
          "max": 0
        },
        "hardness": 0,
        "price": {
          "value": {
            "gp": 6
          }
        },
        "equipped": {
          "carryType": "worn",
          "invested": null,
          "inSlot": true,
          "handsHeld": 0
        },
        "containerId": null,
        "size": "med",
        "material": {
          "type": null,
          "grade": null
        },
        "identification": {
          "status": "identified",
          "unidentified": {
            "name": "",
            "img": "",
            "data": {
              "description": {
                "value": ""
              }
            }
          },
          "misidentified": {}
        },
        "category": "medium",
        "group": "chain",
        "acBonus": 4,
        "strength": 3,
        "dexCap": 5,
        "checkPenalty": -2,
        "speedPenalty": -5,
        "runes": {
          "potency": 0,
          "resilient": 0,
          "property": []
        },
        "subitems": [],
        "dex": {
          "value": 1
        }
      },
      "type": "armor",
      "flags": {
        "core": {
          "sourceId": "Compendium.pf2e.equipment-srd.Item.Kf4eJEXnFPuAsseP"
        }
      },
      "effects": [],
      "folder": null,
      "sort": 0,
      "ownership": {
        "default": 0,
        "zGBP0faGe9s57rxO": 3
      },
      "_stats": {
        "compendiumSource": "Compendium.pf2e.equipment-srd.Item.Kf4eJEXnFPuAsseP",
        "duplicateSource": null,
        "coreVersion": "12.331",
        "systemId": "pf2e",
        "systemVersion": "6.2.2",
        "createdTime": null,
        "modifiedTime": null,
        "lastModifiedBy": null
      },
      "_id": "btaHHvitRQ189BTl"
    }
  ],
  "folder": "ivvuv5KicgDBOClz",
  "flags": {
    "core": {},
    "exportSource": {
      "world": "compendium-project-path",
      "system": "pf2e",
      "coreVersion": "12.331",
      "systemVersion": "6.2.2"
    }
  },
  "_stats": {
    "coreVersion": "12.331",
    "systemId": "pf2e",
    "systemVersion": "6.2.2",
    "createdTime": 1724089623862,
    "modifiedTime": 1724089623862,
    "lastModifiedBy": "zGBP0faGe9s57rxO"
  }
}